dbgpt_client/__init__.py
dbgpt_client/_cli.py
dbgpt_client/_version.py
dbgpt_client/app.py
dbgpt_client/client.py
dbgpt_client/datasource.py
dbgpt_client/evaluation.py
dbgpt_client/flow.py
dbgpt_client/knowledge.py
dbgpt_client/schema.py
dbgpt_client-0.7.4.dist-info/METADATA
dbgpt_client-0.7.4.dist-info/WHEEL
dbgpt_client-0.7.4.dist-info/RECORD
